vicdyf/__init__.py
vicdyf/dataset.py
vicdyf/funcs.py
vicdyf/modules.py
vicdyf/utils.py
vicdyf/vicdyf.py
vicdyf/workflow.py
vicdyf_tiisaishima-0.0.2.dist-info/LICENSE
vicdyf_tiisaishima-0.0.2.dist-info/METADATA
vicdyf_tiisaishima-0.0.2.dist-info/WHEEL
vicdyf_tiisaishima-0.0.2.dist-info/top_level.txt
vicdyf_tiisaishima-0.0.2.dist-info/RECORD
